LICENSE
MANIFEST.in
README.rst
arxiv2speech.py
setup.py
arxiv2speech.egg-info/PKG-INFO
arxiv2speech.egg-info/SOURCES.txt
arxiv2speech.egg-info/dependency_links.txt
arxiv2speech.egg-info/requires.txt
arxiv2speech.egg-info/top_level.txt
scripts/arxiv2speech