Metadata-Version: 1.1
Name: arxiv2speech
Version: 0.0.4
Summary: Convert the current abstracts listed on the arxiv to a set of audio files.
Home-page: https://github.com/dfm/arxiv2speech
Author: Dan Foreman-Mackey
Author-email: danfm@nyu.edu
License: UNKNOWN
Platform: UNKNOWN
Classifier: Development Status :: 3 - Alpha
Classifier: License :: OSI Approved :: BSD License
Classifier: Intended Audience :: Science/Research
Classifier: Programming Language :: Python
Classifier: Programming Language :: Python :: 2.7
Classifier: Programming Language :: Python :: 3.3
